TRXASprefitpack/__init__.py
TRXASprefitpack/driver/__init__.py
TRXASprefitpack/driver/_ampgo.py
TRXASprefitpack/driver/_static_thy.py
TRXASprefitpack/driver/_static_voigt.py
TRXASprefitpack/driver/_transient_both.py
TRXASprefitpack/driver/_transient_dmp_osc.py
TRXASprefitpack/driver/_transient_exp.py
TRXASprefitpack/driver/_transient_raise.py
TRXASprefitpack/driver/ads.py
TRXASprefitpack/driver/anal_fit.py
TRXASprefitpack/driver/static_result.py
TRXASprefitpack/driver/transient_result.py
TRXASprefitpack/mathfun/A_matrix.py
TRXASprefitpack/mathfun/__init__.py
TRXASprefitpack/mathfun/deriv_check.py
TRXASprefitpack/mathfun/exp_conv_irf.py
TRXASprefitpack/mathfun/exp_decay_fit.py
TRXASprefitpack/mathfun/irf.py
TRXASprefitpack/mathfun/peak_shape.py
TRXASprefitpack/mathfun/rate_eq.py
TRXASprefitpack/res/__init__.py
TRXASprefitpack/res/parm_bound.py
TRXASprefitpack/res/res_both.py
TRXASprefitpack/res/res_decay.py
TRXASprefitpack/res/res_osc.py
TRXASprefitpack/res/res_raise.py
TRXASprefitpack/res/res_thy.py
TRXASprefitpack/res/res_voigt.py
TRXASprefitpack/tools/__init__.py
TRXASprefitpack/tools/_calc_broad.py
TRXASprefitpack/tools/_calc_dads.py
TRXASprefitpack/tools/_calc_dads_gui.py
TRXASprefitpack/tools/_calc_sads.py
TRXASprefitpack/tools/_fit_static.py
TRXASprefitpack/tools/_fit_tscan.py
TRXASprefitpack/tools/_fit_tscan_gui.py
TRXASprefitpack/tools/_match_scale.py
TRXASprefitpack/tools/misc.py
TRXASprefitpack-0.8.0.dist-info/METADATA
TRXASprefitpack-0.8.0.dist-info/WHEEL
TRXASprefitpack-0.8.0.dist-info/entry_points.txt
TRXASprefitpack-0.8.0.dist-info/top_level.txt
TRXASprefitpack-0.8.0.dist-info/RECORD
