Metadata-Version: 2.1
Name: TRXASprefitpack
Version: 0.8.0
Summary: package for TRXAS pre-fitting process
Home-page: https://github.com/pistack/TRXASprefitpack
Author: Junho Lee (pistack)
Author-email: phistack@kaist.ac.kr
License: LGPLv3
Platform: any
Classifier: Development Status :: 4 - Beta
Classifier: License :: OSI Approved :: GNU Lesser General Public License v3 (LGPLv3)
Classifier: Programming Language :: Python :: 3
Requires-Dist: numpy>=1.10.1
Requires-Dist: scipy>=0.17.0
Requires-Dist: matplotlib
Requires-Dist: h5py
